clinner/__init__.py
clinner/apps.py
clinner/builder.py
clinner/cli.py
clinner/command.py
clinner/exceptions.py
clinner/inputs.py
clinner/run/__init__.py
clinner/run/base.py
clinner/run/commands/__init__.py
clinner/run/commands/black.py
clinner/run/commands/dist.py
clinner/run/commands/flake8.py
clinner/run/commands/isort.py
clinner/run/commands/nose.py
clinner/run/commands/prospector.py
clinner/run/commands/pytest.py
clinner/run/commands/sphinx.py
clinner/run/commands/tox.py
clinner/run/django_command.py
clinner/run/main.py
clinner/run/mixins/__init__.py
clinner/run/mixins/health_check.py
clinner/settings.py
clinner-1.12.3.dist-info/LICENSE
clinner-1.12.3.dist-info/WHEEL
clinner-1.12.3.dist-info/METADATA
clinner-1.12.3.dist-info/RECORD
