Metadata-Version: 2.1
Name: clinner
Version: 1.12.3
Summary: Command Line Interface builder that helps creating an entry point for your application.
Home-page: https://github.com/PeRDy/clinner
Author: José Antonio Perdiguero López
Author-email: perdy@perdy.io
Keywords: command,cli,interface,run,script
Requires-Python: >=3.5,<4.0
Classifier: License :: OSI Approved :: GNU General Public License v3 or later (GPLv3+)
Classifier: Programming Language :: Python :: 3
Classifier: Programming Language :: Python :: 3.5
Classifier: Programming Language :: Python :: 3.6
Classifier: Programming Language :: Python :: 3.7
Requires-Dist: colorlog (>=3.1,<4.0)
